HISTORY.md
LICENSE
MANIFEST.in
NOTICE
README.md
pyproject.toml
requirements-dev.txt
setup.cfg
setup.py
src/rehttps/__init__.py
src/rehttps/__version__.py
src/rehttps/_internal_utils.py
src/rehttps/adapters.py
src/rehttps/api.py
src/rehttps/auth.py
src/rehttps/certs.py
src/rehttps/compat.py
src/rehttps/cookies.py
src/rehttps/exceptions.py
src/rehttps/help.py
src/rehttps/hooks.py
src/rehttps/models.py
src/rehttps/packages.py
src/rehttps/sessions.py
src/rehttps/status_codes.py
src/rehttps/structures.py
src/rehttps/utils.py
src/rehttps.egg-info/PKG-INFO
src/rehttps.egg-info/SOURCES.txt
src/rehttps.egg-info/dependency_links.txt
src/rehttps.egg-info/not-zip-safe
src/rehttps.egg-info/requires.txt
src/rehttps.egg-info/top_level.txt
tests/__init__.py
tests/compat.py
tests/conftest.py
tests/test_adapters.py
tests/test_help.py
tests/test_hooks.py
tests/test_lowlevel.py
tests/test_packages.py
tests/test_requests.py
tests/test_structures.py
tests/test_testserver.py
tests/test_utils.py
tests/utils.py
tests/certs/README.md
tests/certs/expired/Makefile
tests/certs/expired/README.md
tests/certs/expired/ca/Makefile
tests/certs/expired/ca/ca-private.key
tests/certs/expired/ca/ca.cnf
tests/certs/expired/ca/ca.crt
tests/certs/expired/ca/ca.srl
tests/certs/expired/server/Makefile
tests/certs/expired/server/cert.cnf
tests/certs/expired/server/server.csr
tests/certs/expired/server/server.key
tests/certs/expired/server/server.pem
tests/certs/mtls/Makefile
tests/certs/mtls/README.md
tests/certs/mtls/client/Makefile
tests/certs/mtls/client/cert.cnf
tests/certs/mtls/client/client.csr
tests/certs/mtls/client/client.key
tests/certs/mtls/client/client.pem
tests/certs/mtls/client/ca/Makefile
tests/certs/mtls/client/ca/ca-private.key
tests/certs/mtls/client/ca/ca.cnf
tests/certs/mtls/client/ca/ca.crt
tests/certs/mtls/client/ca/ca.srl
tests/certs/valid/ca/Makefile
tests/certs/valid/ca/ca-private.key
tests/certs/valid/ca/ca.cnf
tests/certs/valid/ca/ca.crt
tests/certs/valid/ca/ca.srl
tests/certs/valid/server/Makefile
tests/certs/valid/server/cert.cnf
tests/certs/valid/server/server.csr
tests/certs/valid/server/server.key
tests/certs/valid/server/server.pem
tests/testserver/__init__.py
